hqg_algorithms/__init__.py
hqg_algorithms/strategy.py
hqg_algorithms/types.py
hqg_algorithms-0.1.0.dist-info/METADATA
hqg_algorithms-0.1.0.dist-info/WHEEL
hqg_algorithms-0.1.0.dist-info/top_level.txt
hqg_algorithms-0.1.0.dist-info/RECORD
