Metadata-Version: 2.4
Name: hqg-algorithms
Version: 0.1.0
Summary: Algorithmic trading research utilities for quant teams
Project-URL: Homepage, https://github.com/yourusername/hqg-algorithms
Requires-Python: >=3.8
